[{"id":"fill_in","label":"Fill-in only","color":"#3b82f6","sort_order":6},{"id":"new","label":"New / Restarting","color":"#06b6d4","sort_order":7},{"id":"not_heard","label":"Not heard from","color":"#6b7280","sort_order":4},{"id":"not_returning","label":"Not returning","color":"#ef4444","sort_order":5},{"id":"planning","label":"Planning to play","color":"#22c55e","sort_order":1},{"id":"unlikely","label":"Unlikely to play","color":"#a855f7","sort_order":3},{"id":"unsure","label":"Unsure","color":"#eab308","sort_order":2}]